fastiot/__init__.py
fastiot/__version__.py
fastiot/testlib.py
fastiot/cli/__init__.py
fastiot/cli/cli_logging.py
fastiot/cli/constants.py
fastiot/cli/env.py
fastiot/cli/fiot.py
fastiot/cli/helper_fn.py
fastiot/cli/import_configure.py
fastiot/cli/infrastructure_service_fn.py
fastiot/cli/typer_app.py
fastiot/cli/version.py
fastiot/cli/commands/__init__.py
fastiot/cli/commands/build.py
fastiot/cli/commands/build_lib.py
fastiot/cli/commands/clean.py
fastiot/cli/commands/config.py
fastiot/cli/commands/create.py
fastiot/cli/commands/deploy.py
fastiot/cli/commands/manage_requirements.py
fastiot/cli/commands/nuitka_compile.py
fastiot/cli/commands/print.py
fastiot/cli/commands/run_tests.py
fastiot/cli/commands/start.py
fastiot/cli/commands/stop.py
fastiot/cli/commands/version.py
fastiot/cli/common/__init__.py
fastiot/cli/common/docker_templates.py
fastiot/cli/common/infrastructure_services.py
fastiot/cli/model/__init__.py
fastiot/cli/model/compose_info.py
fastiot/cli/model/deployment.py
fastiot/cli/model/docker_template.py
fastiot/cli/model/infrastructure_service.py
fastiot/cli/model/manifest.py
fastiot/cli/model/project.py
fastiot/cli/model/service.py
fastiot/cli/templates/Dockerfile.j2
fastiot/cli/templates/ansible-playbook.yaml.j2
fastiot/cli/templates/ansible_hosts.j2
fastiot/cli/templates/docker-bake.hcl.j2
fastiot/cli/templates/docker-compose.yaml.j2
fastiot/cli/templates/pyproject.toml.j2
fastiot/cli/templates/new_project/.dockerignore
fastiot/cli/templates/new_project/.env.j2
fastiot/cli/templates/new_project/.env.production.j2
fastiot/cli/templates/new_project/.gitignore
fastiot/cli/templates/new_project/README.md.j2
fastiot/cli/templates/new_project/__init__.py
fastiot/cli/templates/new_project/configure.py.j2
fastiot/cli/templates/new_project/deployment.yaml
fastiot/cli/templates/new_project/deployment.yaml.j2
fastiot/cli/templates/new_project/dummy_test.py
fastiot/cli/templates/new_project/install.sh
fastiot/cli/templates/new_project/requirements.txt.j2
fastiot-1.1.dist-info/LICENSE
fastiot-1.1.dist-info/METADATA
fastiot-1.1.dist-info/WHEEL
fastiot-1.1.dist-info/entry_points.txt
fastiot-1.1.dist-info/top_level.txt
fastiot-1.1.dist-info/RECORD
