Metadata-Version: 2.1
Name: fastiot
Version: 1.1
Summary: FastIoT Platform
Author-email: Tilman Klaeger <tilman.klaeger@ivv-dd.fraunhofer.de>, Konstantin Merker <konstantin.merker@ivv-dd.fraunhofer.de>, Fraunhofer Institute for Process Engineering and Packaging IVV <info@ivv-dd.fraunhofer.de>
Maintainer-email: Tilman Klaeger <tilman.klaeger@ivv-dd.fraunhofer.de>, Tim Kaluza <tim.kaluza@ivv-dd.fraunhofer.de>, Jialiang Yin <jialiang.yin@ivv-dd.fraunhofer.de>
Project-URL: Homepage, https://github.com/FraunhoferIVV/fastiot
Project-URL: Source, https://github.com/FraunhoferIVV/fastiot
Project-URL: Documentation, https://fastiot.readthedocs.io
Keywords: Industrial IoT,IoT,Industry4.0,IIoT
Classifier: Development Status :: 5 - Production/Stable
Classifier: Intended Audience :: Developers
Classifier: Intended Audience :: Science/Research
Classifier: License :: OSI Approved :: Apache Software License
Classifier: Programming Language :: Python
Classifier: Topic :: Scientific/Engineering
Classifier: Topic :: Software Development :: Libraries :: Application Frameworks
Classifier: Topic :: Software Development :: Libraries :: Python Modules
Classifier: Typing :: Typed
Requires-Python: >=3.9
License-File: LICENSE
Requires-Dist: pydantic <2,>=1.9.0
Requires-Dist: msgpack <2,>=1
Requires-Dist: nats-py <=6,>=2.3.0
Requires-Dist: PyYAML <7,>=5
Provides-Extra: compile
Requires-Dist: Nuitka <2,>=1.1.7 ; extra == 'compile'
Requires-Dist: ordered-set ; extra == 'compile'
Provides-Extra: dash
Requires-Dist: dash ~=2.6.1 ; extra == 'dash'
Requires-Dist: plotly ~=5.9.0 ; extra == 'dash'
Requires-Dist: numpy ; extra == 'dash'
Requires-Dist: pandas ; extra == 'dash'
Requires-Dist: dash-bootstrap-components ; extra == 'dash'
Requires-Dist: xlsxwriter ; extra == 'dash'
Requires-Dist: nest-asyncio ; extra == 'dash'
Requires-Dist: pymongo <5,>=4.1 ; extra == 'dash'
Provides-Extra: dev
Requires-Dist: pytest <8,>=7.2 ; extra == 'dev'
Requires-Dist: typer[all] <1,>=0.4.1 ; extra == 'dev'
Requires-Dist: tomli ~=2.0.1 ; extra == 'dev'
Requires-Dist: tomli-w ; extra == 'dev'
Requires-Dist: build ; extra == 'dev'
Requires-Dist: pip-tools ; extra == 'dev'
Requires-Dist: typer <1,>=0.4.1 ; extra == 'dev'
Requires-Dist: Jinja2 <4,>=2 ; extra == 'dev'
Requires-Dist: pytest-cov >=4.1.0 ; extra == 'dev'
Provides-Extra: docs
Requires-Dist: sphinx <7,>=5 ; extra == 'docs'
Requires-Dist: sphinx-automodapi ; extra == 'docs'
Requires-Dist: sphinx-autodoc-typehints ; extra == 'docs'
Requires-Dist: recommonmark ; extra == 'docs'
Requires-Dist: myst-parser ; extra == 'docs'
Requires-Dist: autodoc-pydantic ; extra == 'docs'
Requires-Dist: sphinx-material ; extra == 'docs'
Requires-Dist: sphinx-click ; extra == 'docs'
Requires-Dist: sphinx-rtd-theme ; extra == 'docs'
Provides-Extra: fastapi
Requires-Dist: fastapi ; extra == 'fastapi'
Requires-Dist: aiofiles ; extra == 'fastapi'
Requires-Dist: uvicorn[standard] ; extra == 'fastapi'
Provides-Extra: influxdb
Requires-Dist: influxdb-client[async] <2,>=1.32 ; extra == 'influxdb'
Provides-Extra: mariadb
Requires-Dist: PyMySQL <2,>=1.0 ; extra == 'mariadb'
Provides-Extra: mongodb
Requires-Dist: pymongo <5,>=4.1 ; extra == 'mongodb'
Provides-Extra: opcua
Requires-Dist: opcua <1,>=0.98.8 ; extra == 'opcua'
Requires-Dist: asyncua ; extra == 'opcua'
Provides-Extra: postgredb
Requires-Dist: psycopg2-binary <3,>=2.9.3 ; extra == 'postgredb'
Provides-Extra: redis
Requires-Dist: Redis >4 ; extra == 'redis'
